[
    {
        "dustbin_id": "001",
        "status": "Finished",
        "color": "green",
        "image": "uploads\/dustbin_1745706282.jpeg",
        "timestamp": "2025-04-26T22:27:08.053Z"
    },
     {
        "dustbin_id": "002",
        "status": "Finished",
        "color": "green",
        "image": "uploads\/dustbin_1745706282.jpeg",
        "timestamp": "2025-04-26T22:32:37.327Z"
    },
 {
        "dustbin_id": "003",
        "status": "Finished",
        "color": "green",
        "image": "uploads\/dustbin_1745706282.jpeg",
        "timestamp": "2025-04-26T22:52:35.755Z"
    },
     {
        "dustbin_id": "004",
        "status": "Finished",
        "color": "blue",
        "image": "uploads\/dustbin_1745729118.jpeg",
        "timestamp": "2025-04-27T04:48:41.363Z"
    },
     {
        "dustbin_id": "005",
        "status": "Finished",
        "color": "blue",
        "image": "uploads\/dustbin_1745729118.jpeg",
        "timestamp": "2025-04-27T04:59:48.993Z"
    },
{
        "dustbin_id": "006",
        "status": "Finished",
        "color": "blue",
        "image": "uploads\/dustbin_1745729118.jpeg",
        "timestamp": "2025-04-29T07:59:38.266Z"
    },
